iaswn/#__init__.py#
iaswn/__init__.py
iaswn/aboutproject.py
iaswn/iaswn.py
iaswn-0.1.11.dist-info/LICENSE
iaswn-0.1.11.dist-info/WHEEL
iaswn-0.1.11.dist-info/METADATA
iaswn-0.1.11.dist-info/RECORD
